resource_namer/__init__.py
resource_namer/__main__.py
resource_namer/__meta__.py
resource_namer/word_lists.py
resource_namer-1.0.5.dist-info/LICENSE
resource_namer-1.0.5.dist-info/METADATA
resource_namer-1.0.5.dist-info/WHEEL
resource_namer-1.0.5.dist-info/top_level.txt
resource_namer-1.0.5.dist-info/RECORD
