Metadata-Version: 2.1
Name: resource-namer
Version: 1.0.5
Summary: Generate names for things with phonetic alliteration - use with GUIDs for easy identification.
Home-page: https://github.com/darenr/resource-namer
Author: Daren Race
Author-email: daren.race@gmail.com
License: Apache License, Version 2.0, January 2004
Keywords: random resource name generator
Platform: UNKNOWN
Classifier: Development Status :: 5 - Production/Stable
Classifier: Topic :: Software Development :: Libraries :: Application Frameworks
Classifier: License :: OSI Approved :: Apache Software License
Classifier: Programming Language :: Python :: 3.7
Classifier: Programming Language :: Python :: 3.8
Classifier: Programming Language :: Python :: 3.9
Classifier: Programming Language :: Python :: 3.10
License-File: LICENSE
